faker_mobile_bank_clickstream/__init__.py
faker_mobile_bank_clickstream/clickstream.py
faker_mobile_bank_clickstream/event_constants.py
faker_mobile_bank_clickstream/ip.py
faker_mobile_bank_clickstream/user_agents.py
faker_mobile_bank_clickstream-1.1.1.dist-info/LICENSE
faker_mobile_bank_clickstream-1.1.1.dist-info/METADATA
faker_mobile_bank_clickstream-1.1.1.dist-info/WHEEL
faker_mobile_bank_clickstream-1.1.1.dist-info/top_level.txt
faker_mobile_bank_clickstream-1.1.1.dist-info/zip-safe
faker_mobile_bank_clickstream-1.1.1.dist-info/RECORD
